metaflow_extensions/card_uplot/plugins/cards/uplot/__init__.py
metaflow_extensions/card_uplot/plugins/cards/uplot/uplot/LICENSE.txt
metaflow_extensions/card_uplot/plugins/cards/uplot/uplot/card.html
metaflow_extensions/card_uplot/plugins/cards/uplot/uplot/uPlot.iife.min.js
metaflow_extensions/card_uplot/plugins/cards/uplot/uplot/uPlot.min.css
metaflow_card_uplot-1.0.0.dist-info/METADATA
metaflow_card_uplot-1.0.0.dist-info/WHEEL
metaflow_card_uplot-1.0.0.dist-info/top_level.txt
metaflow_card_uplot-1.0.0.dist-info/RECORD
