Metadata-Version: 2.1
Name: metaflow-card-uplot
Version: 1.0.0
Summary: A Metaflow card to visualize timeseries dataframes using Uplot
Home-page: UNKNOWN
Author: Valay Dave
Author-email: valay@outerbounds.co
License: Apache Software License 2.0
Platform: UNKNOWN
